Processing/__init__.py
Processing/combination.py
Processing/transformation.py
utils/__init__.py
utils/io.py
utils/plot.py
processador_de_imagem_zoemateus324-0.0.2.dist-info/METADATA
processador_de_imagem_zoemateus324-0.0.2.dist-info/WHEEL
processador_de_imagem_zoemateus324-0.0.2.dist-info/top_level.txt
processador_de_imagem_zoemateus324-0.0.2.dist-info/RECORD
