Metadata-Version: 2.4
Name: processador-de-imagem-zoemateus324
Version: 0.0.2
Summary: My first application of image processing with python language
Home-page: https://github.com/Zoemateus324/processador-de-imagem
Author: Zoe Santos
Author-email: zmmateus2@gmail.com
Requires-Python: >=3.8
Requires-Dist: matplotlib
Requires-Dist: numpy
Requires-Dist: scikit-image>0.16.1
Dynamic: author
Dynamic: author-email
Dynamic: description
Dynamic: description-content-type
Dynamic: home-page
Dynamic: requires-dist
Dynamic: requires-python
Dynamic: summary
